gcs_easy/__init__.py
gcs_easy/auth.py
gcs_easy/cli.py
gcs_easy/client.py
gcs_easy/permissions_checker.py
gcs_easy-0.1.3.dist-info/METADATA
gcs_easy-0.1.3.dist-info/WHEEL
gcs_easy-0.1.3.dist-info/entry_points.txt
gcs_easy-0.1.3.dist-info/licenses/LICENSE
gcs_easy-0.1.3.dist-info/RECORD
