Metadata-Version: 2.4
Name: gcs-easy
Version: 0.1.3
Summary: Autenticación sencilla y utilidades para Google Cloud Storage (subir, bajar, firmar URLs).
Author-email: Juan Manuel <juanmanuelcabrera.r@gmail.com>
License-Expression: MIT
License-File: LICENSE
Requires-Python: >=3.9
Requires-Dist: google-auth-oauthlib>=1.2.1
Requires-Dist: google-auth>=2.33.0
Requires-Dist: google-cloud-storage>=2.18.0
Requires-Dist: python-dotenv>=1.0.0
Requires-Dist: pyyaml>=6.0
Requires-Dist: tqdm>=4.66.0
Provides-Extra: test
Requires-Dist: pytest-mock>=3.0.0; extra == 'test'
Requires-Dist: pytest>=7.0.0; extra == 'test'
